iflow_mcp_norman_finance_norman_mcp_server-0.1.8.dist-info/licenses/LICENSE
norman_mcp/__init__.py
norman_mcp/__main__.py
norman_mcp/cli.py
norman_mcp/context.py
norman_mcp/server.py
norman_mcp/__pycache__/__init__.cpython-311.pyc
norman_mcp/__pycache__/__main__.cpython-311.pyc
norman_mcp/__pycache__/cli.cpython-311.pyc
norman_mcp/__pycache__/context.cpython-311.pyc
norman_mcp/__pycache__/server.cpython-311.pyc
norman_mcp/api/__init__.py
norman_mcp/api/client.py
norman_mcp/api/__pycache__/__init__.cpython-311.pyc
norman_mcp/api/__pycache__/client.cpython-311.pyc
norman_mcp/auth/README.md
norman_mcp/auth/__init__.py
norman_mcp/auth/provider.py
norman_mcp/auth/routes.py
norman_mcp/auth/__pycache__/__init__.cpython-311.pyc
norman_mcp/auth/__pycache__/provider.cpython-311.pyc
norman_mcp/auth/__pycache__/routes.cpython-311.pyc
norman_mcp/auth/templates/login.html
norman_mcp/config/__init__.py
norman_mcp/config/settings.py
norman_mcp/config/__pycache__/__init__.cpython-311.pyc
norman_mcp/config/__pycache__/settings.cpython-311.pyc
norman_mcp/prompts/__init__.py
norman_mcp/prompts/templates.py
norman_mcp/prompts/__pycache__/__init__.cpython-311.pyc
norman_mcp/prompts/__pycache__/templates.cpython-311.pyc
norman_mcp/resources/__init__.py
norman_mcp/resources/endpoints.py
norman_mcp/resources/__pycache__/__init__.cpython-311.pyc
norman_mcp/resources/__pycache__/endpoints.cpython-311.pyc
norman_mcp/security/__init__.py
norman_mcp/security/utils.py
norman_mcp/security/__pycache__/__init__.cpython-311.pyc
norman_mcp/security/__pycache__/utils.cpython-311.pyc
norman_mcp/tools/__init__.py
norman_mcp/tools/clients.py
norman_mcp/tools/company.py
norman_mcp/tools/documents.py
norman_mcp/tools/invoices.py
norman_mcp/tools/taxes.py
norman_mcp/tools/transactions.py
norman_mcp/tools/__pycache__/__init__.cpython-311.pyc
norman_mcp/tools/__pycache__/clients.cpython-311.pyc
norman_mcp/tools/__pycache__/company.cpython-311.pyc
norman_mcp/tools/__pycache__/documents.cpython-311.pyc
norman_mcp/tools/__pycache__/invoices.cpython-311.pyc
iflow_mcp_norman_finance_norman_mcp_server-0.1.8.dist-info/METADATA
iflow_mcp_norman_finance_norman_mcp_server-0.1.8.dist-info/WHEEL
iflow_mcp_norman_finance_norman_mcp_server-0.1.8.dist-info/entry_points.txt
iflow_mcp_norman_finance_norman_mcp_server-0.1.8.dist-info/top_level.txt
iflow_mcp_norman_finance_norman_mcp_server-0.1.8.dist-info/RECORD
