Metadata-Version: 2.4
Name: iflow-mcp_norman-finance_norman-mcp-server
Version: 0.1.8
Summary: A Model Context Protocol (MCP) server for Norman Finance API
Author-email: Norman Finance <stan@norman.finance>
License: MIT
Project-URL: Homepage, https://github.com/norman-finance/norman-mcp-server
Project-URL: Issues, https://github.com/norman-finance/norman-mcp-server/issues
Classifier: Development Status :: 4 - Beta
Classifier: Intended Audience :: Developers
Classifier: License :: OSI Approved :: MIT License
Classifier: Programming Language :: Python :: 3
Classifier: Programming Language :: Python :: 3.9
Classifier: Programming Language :: Python :: 3.10
Classifier: Programming Language :: Python :: 3.11
Requires-Python: >=3.10
License-File: LICENSE
Requires-Dist: mcp>=0.3.0
Requires-Dist: mcp[cli]>=1.7.0
Requires-Dist: requests>=2.25.0
Requires-Dist: python-dotenv>=0.19.0
Requires-Dist: pyyaml>=6.0.1
Requires-Dist: httpx>=0.24.0
Requires-Dist: jinja2>=3.0.0
Provides-Extra: dev
Requires-Dist: pytest>=6.0.0; extra == "dev"
Requires-Dist: black>=22.3.0; extra == "dev"
Requires-Dist: isort>=5.10.1; extra == "dev"
Requires-Dist: flake8>=4.0.0; extra == "dev"
Requires-Dist: mypy>=0.942; extra == "dev"
Provides-Extra: sse
Requires-Dist: fastapi>=0.95.0; extra == "sse"
Requires-Dist: uvicorn>=0.22.0; extra == "sse"
Requires-Dist: pydantic>=2.0.0; extra == "sse"
Dynamic: license-file
